inductiveGRL/__init__.py
inductiveGRL/evaluation.py
inductiveGRL/graphconstruction.py
inductiveGRL/hinsage.py
inductiveGRL/timeframes.py
inductiveGRL-0.2.dist-info/METADATA
inductiveGRL-0.2.dist-info/WHEEL
inductiveGRL-0.2.dist-info/top_level.txt
inductiveGRL-0.2.dist-info/RECORD
